Metadata-Version: 2.1
Name: tabrec-v
Version: 0.0.2
Summary: tabrec-v
Home-page: 
Author: jaemin92
Author-email: 
License: Apache License 2.0
Requires-Python: >=3.8
Requires-Dist: absl-py ==2.1.0
Requires-Dist: addict ==2.4.0
Requires-Dist: aiofiles ==24.1.0
Requires-Dist: albucore ==0.0.13
Requires-Dist: albumentations ==1.4.14
Requires-Dist: annotated-types ==0.7.0
Requires-Dist: anyio ==4.4.0
Requires-Dist: appnope ==0.1.4
Requires-Dist: asttokens ==2.4.1
Requires-Dist: backcall ==0.2.0
Requires-Dist: cachetools ==5.5.0
Requires-Dist: certifi ==2024.7.4
Requires-Dist: charset-normalizer ==3.3.2
Requires-Dist: ci-info ==0.3.0
Requires-Dist: click ==8.1.7
Requires-Dist: coloredlogs ==15.0.1
Requires-Dist: configobj ==5.0.8
Requires-Dist: configparser ==7.1.0
Requires-Dist: contourpy ==1.1.1
Requires-Dist: cycler ==0.12.1
Requires-Dist: decorator ==5.1.1
Requires-Dist: etelemetry ==0.3.1
Requires-Dist: eval-type-backport ==0.2.0
Requires-Dist: exceptiongroup ==1.2.2
Requires-Dist: executing ==2.0.1
Requires-Dist: filelock ==3.15.4
Requires-Dist: flatbuffers ==24.3.25
Requires-Dist: fonttools ==4.53.1
Requires-Dist: frontend ==0.0.3
Requires-Dist: fsspec ==2024.6.1
Requires-Dist: gitdb ==4.0.11
Requires-Dist: GitPython ==3.1.43
Requires-Dist: google-auth ==2.34.0
Requires-Dist: google-auth-oauthlib ==1.0.0
Requires-Dist: grpcio ==1.66.0
Requires-Dist: h11 ==0.14.0
Requires-Dist: httplib2 ==0.22.0
Requires-Dist: huggingface-hub ==0.24.6
Requires-Dist: humanfriendly ==10.0
Requires-Dist: idna ==3.8
Requires-Dist: imageio ==2.35.1
Requires-Dist: importlib-metadata ==8.4.0
Requires-Dist: importlib-resources ==6.4.4
Requires-Dist: ipython ==8.12.3
Requires-Dist: isodate ==0.6.1
Requires-Dist: itsdangerous ==2.2.0
Requires-Dist: jedi ==0.19.1
Requires-Dist: Jinja2 ==3.1.4
Requires-Dist: kiwisolver ==1.4.5
Requires-Dist: lazy-loader ==0.4
Requires-Dist: looseversion ==1.3.0
Requires-Dist: lxml ==5.3.0
Requires-Dist: Markdown ==3.7
Requires-Dist: markdown-it-py ==3.0.0
Requires-Dist: MarkupSafe ==2.1.5
Requires-Dist: matplotlib ==3.7.5
Requires-Dist: matplotlib-inline ==0.1.7
Requires-Dist: mdurl ==0.1.2
Requires-Dist: mpmath ==1.3.0
Requires-Dist: networkx ==3.1
Requires-Dist: nibabel ==5.2.1
Requires-Dist: nipype ==1.8.6
Requires-Dist: numpy ==1.24.4
Requires-Dist: oauthlib ==3.2.2
Requires-Dist: onnx ==1.16.2
Requires-Dist: onnxruntime ==1.19.0
Requires-Dist: opencv-python ==4.10.0.84
Requires-Dist: opencv-python-headless ==4.10.0.84
Requires-Dist: packaging ==24.1
Requires-Dist: pandas ==2.0.3
Requires-Dist: parso ==0.8.4
Requires-Dist: pathlib ==1.0.1
Requires-Dist: pexpect ==4.9.0
Requires-Dist: pickleshare ==0.7.5
Requires-Dist: pillow ==10.4.0
Requires-Dist: platformdirs ==4.2.2
Requires-Dist: prompt-toolkit ==3.0.47
Requires-Dist: protobuf ==5.27.3
Requires-Dist: prov ==2.0.1
Requires-Dist: psutil ==6.0.0
Requires-Dist: ptyprocess ==0.7.0
Requires-Dist: pure-eval ==0.2.3
Requires-Dist: py-cpuinfo ==9.0.0
Requires-Dist: pyasn1 ==0.6.0
Requires-Dist: pyasn1-modules ==0.4.0
Requires-Dist: pycocotools ==2.0.7
Requires-Dist: pydantic ==2.8.2
Requires-Dist: pydantic-settings ==2.4.0
Requires-Dist: pydantic-core ==2.20.1
Requires-Dist: pydot ==3.0.1
Requires-Dist: Pygments ==2.18.0
Requires-Dist: PyMuPDF ==1.24.9
Requires-Dist: PyMuPDFb ==1.24.9
Requires-Dist: pyparsing ==3.1.4
Requires-Dist: python-dateutil ==2.9.0.post0
Requires-Dist: python-dotenv ==1.0.1
Requires-Dist: pytz ==2024.1
Requires-Dist: PyWavelets ==1.4.1
Requires-Dist: pyxnat ==1.6.2
Requires-Dist: PyYAML ==6.0.2
Requires-Dist: rdflib ==6.3.2
Requires-Dist: requests ==2.32.3
Requires-Dist: requests-oauthlib ==2.0.0
Requires-Dist: rich ==13.7.1
Requires-Dist: rsa ==4.9
Requires-Dist: safetensors ==0.4.4
Requires-Dist: scikit-image ==0.21.0
Requires-Dist: scipy ==1.10.1
Requires-Dist: seaborn ==0.13.2
Requires-Dist: simplejson ==3.19.3
Requires-Dist: six ==1.16.0
Requires-Dist: smmap ==5.0.1
Requires-Dist: sniffio ==1.3.1
Requires-Dist: stack-data ==0.6.3
Requires-Dist: starlette ==0.38.2
Requires-Dist: sympy ==1.13.2
Requires-Dist: tensorboard ==2.14.0
Requires-Dist: tensorboard-data-server ==0.7.2
Requires-Dist: termcolor ==2.4.0
Requires-Dist: thop ==0.1.1.post2209072238
Requires-Dist: tifffile ==2023.7.10
Requires-Dist: timm ==1.0.9
Requires-Dist: tomli ==2.0.1
Requires-Dist: tqdm ==4.66.5
Requires-Dist: traitlets ==5.14.3
Requires-Dist: traits ==6.3.2
Requires-Dist: typing-extensions ==4.12.2
Requires-Dist: tzdata ==2024.1
Requires-Dist: urllib3 ==2.2.2
Requires-Dist: uvicorn ==0.30.6
Requires-Dist: wcwidth ==0.2.13
Requires-Dist: Werkzeug ==3.0.4
Requires-Dist: yapf ==0.40.2
Requires-Dist: zipp ==3.20.0
